{
  "version": 1,
  "dependencies": [
    {
      "source": {
        "git": {
          "remote": "https://github.com/grafana/alloy.git",
          "subdir": "operations/alloy-mixin"
        }
      },
      "version": "214386005f135c7b3117cc0555427e16285eff16",
      "sum": "5P3W24eINzSOmpt4XwvRRiqc1DS0KfQ/T+Kzs9K2Qxo="
    },
    {
      "source": {
        "git": {
          "remote": "https://github.com/grafana/grafonnet.git",
          "subdir": "gen/grafonnet-v10.0.0"
        }
      },
      "version": "42d098fae987f25f08480e203ca6ddc548c6efbf",
      "sum": "xdcrJPJlpkq4+5LpGwN4tPAuheNNLXZjE6tDcyvFjr0="
    },
    {
      "source": {
        "git": {
          "remote": "https://github.com/grafana/grafonnet.git",
          "subdir": "gen/grafonnet-v11.0.0"
        }
      },
      "version": "42d098fae987f25f08480e203ca6ddc548c6efbf",
      "sum": "0BvzR0i4bS4hc2O3xDv6i9m52z7mPrjvqxtcPrGhynA="
    },
    {
      "source": {
        "git": {
          "remote": "https://github.com/grafana/jsonnet-libs.git",
          "subdir": "logs-lib/"
        }
      },
      "version": "b1b63e77d305a331d31fe008e04d259f0231f502",
      "sum": "0xwYsW92n4rE9PfO3drN4Ko9VeQBoV/IZ7nvgrnYaWk="
    },
    {
      "source": {
        "git": {
          "remote": "https://github.com/grafana/jsonnet-libs.git",
          "subdir": "logs-lib/logs"
        }
      },
      "version": "b1b63e77d305a331d31fe008e04d259f0231f502",
      "sum": "PX1ePJnTxPi4x2bmrbrbC6IPxjOX4p0Fv+H8JOiod5g="
    },
    {
      "source": {
        "git": {
          "remote": "https://github.com/jsonnet-libs/docsonnet.git",
          "subdir": "doc-util"
        }
      },
      "version": "6ac6c69685b8c29c54515448eaca583da2d88150",
      "sum": "BrAL/k23jq+xy9oA7TWIhUx07dsA/QLm3g7ktCwe//U="
    },
    {
      "source": {
        "git": {
          "remote": "https://github.com/jsonnet-libs/xtd.git",
          "subdir": ""
        }
      },
      "version": "4eee017d21cb63a303925d1dcd9fc5c496809b46",
      "sum": "Kh0GbIycNmJPzk6IOMXn1BbtLNyaiiimclYk7+mvsns="
    }
  ],
  "legacyImports": false
}
